scikit_learn_emeralds-0.0.4.1.dist-info/licenses/LICENSE
skl_emeralds/__init__.py
skl_emeralds/argrelextrema.py
skl_emeralds/autohistogram.py
skl_emeralds/confusion_matrix.py
skl_emeralds/integration.py
skl_emeralds/print.py
skl_emeralds/test_train_splitters/__init__.py
skl_emeralds/test_train_splitters/exhaust.py
skl_emeralds/test_train_splitters/oversample.py
skl_emeralds/test_train_splitters/stratify.py
scikit_learn_emeralds-0.0.4.1.dist-info/METADATA
scikit_learn_emeralds-0.0.4.1.dist-info/WHEEL
scikit_learn_emeralds-0.0.4.1.dist-info/top_level.txt
scikit_learn_emeralds-0.0.4.1.dist-info/RECORD
