Metadata-Version: 2.4
Name: scikit-learn-emeralds
Version: 0.0.4.1
Summary: Collection of utils for scikit-learn & scipy
Author-email: "Egil Moeller, Craig W. Christensen, et al." <em@emeraldgeo.no>
License: MIT License
Project-URL: Homepage, https://github.com/emerald-geomodelling/scikit-learn-emeralds
Project-URL: Repository, https://github.com/emerald-geomodelling/scikit-learn-emeralds
Requires-Python: >=3.9
License-File: LICENSE
Requires-Dist: seaborn>=0.12
Requires-Dist: pandas>=1.5
Requires-Dist: numpy>=1.24
Requires-Dist: scipy>=1.10
Provides-Extra: dev
Requires-Dist: pytest>=7.0; extra == "dev"
Requires-Dist: pytest-cov>=4.0; extra == "dev"
Dynamic: license-file
